{"options":[{"enabled":false,"definition":{"id":"5d58cc01-7c75-450c-be18-a388ddb129ec"},"inputs":{"branchFilters":"[\"+refs/heads/*\"]","additionalFields":"{}"}},{"enabled":false,"definition":{"id":"a9db38f9-9fdc-478c-b0f9-464221e58316"},"inputs":{"workItemType":"722186","assignToRequestor":"true","additionalFields":"{}"}}],"triggers":[{"branchFilters":["+refs/heads/master"],"pathFilters":[],"batchChanges":false,"maxConcurrentBuildsPerBranch":1,"pollingInterval":0,"triggerType":2}],"variables":{"system.debug":{"value":"false","allowOverride":true}},"retentionRules":[{"branches":["+refs/heads/*"],"artifacts":[],"artifactTypesToDelete":["FilePath","SymbolStore"],"daysToKeep":10,"minimumToKeep":1,"deleteBuildRecord":true,"deleteTestResults":true}],"properties":{},"tags":[],"_links":{"self":{"href":"https://mrrodant.visualstudio.com/e1780778-4290-42af-a5d6-b43a42dc24db/_apis/build/Definitions/7?revision=1"},"web":{"href":"https://mrrodant.visualstudio.com/e1780778-4290-42af-a5d6-b43a42dc24db/_build/definition?definitionId=7"},"editor":{"href":"https://mrrodant.visualstudio.com/e1780778-4290-42af-a5d6-b43a42dc24db/_build/designer?id=7&_a=edit-build-definition"},"badge":{"href":"https://mrrodant.visualstudio.com/e1780778-4290-42af-a5d6-b43a42dc24db/_apis/build/status/7"}},"jobAuthorizationScope":1,"jobTimeoutInMinutes":60,"jobCancelTimeoutInMinutes":5,"process":{"phases":[{"steps":[{"environment":{},"enabled":true,"continueOnError":false,"alwaysRun":false,"displayName":"npm install","timeoutInMinutes":0,"refName":"Npm1","task":{"id":"fe47e961-9fa8-4106-8639-368c022d43ad","versionSpec":"1.*","definitionType":"task"},"inputs":{"command":"install","workingDir":"","verbose":"false","customCommand":"","customRegistry":"useNpmrc","customFeed":"","customEndpoint":"","publishRegistry":"useExternalRegistry","publishFeed":"","publishEndpoint":""}},{"environment":{},"enabled":true,"continueOnError":false,"alwaysRun":false,"displayName":"Maven","timeoutInMinutes":0,"refName":"Maven2","task":{"id":"ac4ee482-65da-4485-a532-7b085873e532","versionSpec":"1.*","definitionType":"task"},"inputs":{"mavenPOMFile":"pom.xml","goals":"package","options":"","publishJUnitResults":"true","testResultsFiles":"**/TEST-*.xml","testRunTitle":"","codeCoverageTool":"None","classFilter":"","classFilesDirectories":"","srcDirectories":"","failIfCoverageEmpty":"false","javaHomeSelection":"JDKVersion","jdkVersion":"default","jdkUserInputPath":"","jdkArchitecture":"x86","mavenVersionSelection":"Default","mavenPath":"","mavenSetM2Home":"false","mavenOpts":"-Xmx1024m","mavenFeedAuthenticate":"true","sqAnalysisEnabled":"false","sqConnectedServiceName":"","sqProjectName":"","sqProjectKey":"","sqProjectVersion":"","sqDbDetailsRequired":"false","sqDbUrl":"","sqDbUsername":"","sqDbPassword":"","sqAnalysisIncludeFullReport":"true","sqAnalysisBreakBuildIfQualityGateFailed":"false","checkstyleAnalysisEnabled":"false","pmdAnalysisEnabled":"false","findbugsAnalysisEnabled":"false"}},{"environment":{},"enabled":true,"continueOnError":false,"alwaysRun":false,"displayName":"WhiteSource Bolt","timeoutInMinutes":0,"refName":"WhiteSourceBolt3","task":{"id":"521d1e00-f5fb-4b73-a93b-b2fe88a9af91","versionSpec":"","definitionType":"task"},"inputs":{"cwd":"WebGoat","advance":"false","exclude":"","extraFolders":""}},{"environment":{},"enabled":true,"continueOnError":false,"alwaysRun":false,"displayName":"Copy Files","timeoutInMinutes":0,"refName":"CopyFiles4","task":{"id":"5bfb729a-a7c8-4a78-a7c3-8d717bb7c13c","versionSpec":"2.*","definitionType":"task"},"inputs":{"SourceFolder":"$(build.sourcesdirectory)","Contents":"**/*.jar","TargetFolder":"$(build.artifactstagingdirectory)","CleanTargetFolder":"false","OverWrite":"false","flattenFolders":"false"}},{"environment":{},"enabled":true,"continueOnError":false,"alwaysRun":false,"displayName":"Publish Artifact","timeoutInMinutes":0,"refName":"PublishBuildArtifacts5","task":{"id":"2ff763a7-ce83-4e1f-bc89-0ae63477cebe","versionSpec":"1.*","definitionType":"task"},"inputs":{"PathtoPublish":"$(build.artifactstagingdirectory)","ArtifactName":"drop","ArtifactType":"Container","TargetPath":"\\\\my\\share\\$(Build.DefinitionName)\\$(Build.BuildNumber)","Parallel":"false","ParallelCount":"8"}}],"name":null,"refName":"Phase_1","target":{"executionOptions":null,"allowScriptsAuthAccessOption":false,"type":1},"jobAuthorizationScope":0}],"type":1},"repository":{"properties":{"cleanOptions":"0","labelSources":"0","labelSourcesFormat":"$(build.buildNumber)","reportBuildStatus":"true","gitLfsSupport":"false","skipSyncSource":"false","checkoutNestedSubmodules":"false","fetchDepth":"0"},"id":"26749a8c-aa55-431a-93e1-e5be81cc4a1a","type":"TfsGit","name":"WebGoat","url":"https://mrrodant.visualstudio.com/MsReadyWhiteSource/_git/WebGoat","defaultBranch":"refs/heads/master","clean":"false","checkoutSubmodules":false},"processParameters":{},"quality":1,"authoredBy":{"displayName":"Rodrigo Antunes","url":"https://app.vssps.visualstudio.com/A54ce9761-51bb-4a26-a4f5-1c19a57402b8/_apis/Identities/0dbf009e-02df-4433-97f7-dafbf974ddd1","_links":{"avatar":{"href":"https://mrrodant.visualstudio.com/_apis/GraphProfile/MemberAvatars/aad.ZTQ0ZmUyMTMtY2I0ZS03ZWY1LWIzNGItZTMxNTJlMGNiYWVm"}},"id":"0dbf009e-02df-4433-97f7-dafbf974ddd1","uniqueName":"rodant@microsoft.com","imageUrl":"https://mrrodant.visualstudio.com/_api/_common/identityImage?id=0dbf009e-02df-4433-97f7-dafbf974ddd1","descriptor":"aad.ZTQ0ZmUyMTMtY2I0ZS03ZWY1LWIzNGItZTMxNTJlMGNiYWVm"},"drafts":[],"queue":{"_links":{"self":{"href":"https://mrrodant.visualstudio.com/_apis/build/Queues/68"}},"id":68,"name":"Hosted","url":"https://mrrodant.visualstudio.com/_apis/build/Queues/68","pool":{"id":2,"name":"Hosted","isHosted":true}},"id":7,"name":"WhiteSourceBolt","url":"https://mrrodant.visualstudio.com/e1780778-4290-42af-a5d6-b43a42dc24db/_apis/build/Definitions/7?revision=1","uri":"vstfs:///Build/Definition/7","path":"\\","type":2,"queueStatus":0,"revision":1,"createdDate":"2019-01-17T17:41:13.377Z","project":{"id":"e1780778-4290-42af-a5d6-b43a42dc24db","name":"MsReadyWhiteSource","description":"Generated by Azure DevOps Demo Generator","url":"https://mrrodant.visualstudio.com/_apis/projects/e1780778-4290-42af-a5d6-b43a42dc24db","state":1,"revision":98,"visibility":0,"lastUpdateTime":"2019-01-17T17:40:57.767Z"}}